ndx_tan_lab_mesh_attributes/__init__.py
ndx_tan_lab_mesh_attributes/spec/ndx-tan-lab-mesh-attributes.extensions.yaml
ndx_tan_lab_mesh_attributes/spec/ndx-tan-lab-mesh-attributes.namespace.yaml
tests/__init__.py
tests/test_mesh_attributes.py
ndx_tan_lab_mesh_attributes-0.1.0.dist-info/LICENSE.txt
ndx_tan_lab_mesh_attributes-0.1.0.dist-info/METADATA
ndx_tan_lab_mesh_attributes-0.1.0.dist-info/WHEEL
ndx_tan_lab_mesh_attributes-0.1.0.dist-info/top_level.txt
ndx_tan_lab_mesh_attributes-0.1.0.dist-info/RECORD
