Metadata-Version: 2.1
Name: ndx-tan-lab-mesh-attributes
Version: 0.1.0
Summary: Extension for storing attributes of 3D meshes
Home-page: UNKNOWN
Author: Marike Reimer
Author-email: marike.reimer@yale.edu
License: BSD 3-Clause
Platform: UNKNOWN
Classifier: Intended Audience :: Developers
Classifier: Intended Audience :: Science/Research
Requires-Dist: pynwb (>=1.3.0)
